bettersanic.py
bettersanic-1.1.0.dist-info/licenses/LICENSE
bettersanic-1.1.0.dist-info/METADATA
bettersanic-1.1.0.dist-info/WHEEL
bettersanic-1.1.0.dist-info/top_level.txt
bettersanic-1.1.0.dist-info/RECORD
