Metadata-Version: 2.4
Name: bettersanic
Version: 1.1.0
Summary: Sanic with discord.py-like cogs and extensions.
Home-page: https://github.com/HyperKiko/bettersanic
Author: Kiko
License-File: LICENSE
Requires-Dist: sanic
Dynamic: license-file
